lara_django_people/__init__.py
lara_django_people/adapters.py
lara_django_people/admin.py
lara_django_people/apps.py
lara_django_people/context_processors.py
lara_django_people/filters.py
lara_django_people/forms.py
lara_django_people/models.py
lara_django_people/signals.py
lara_django_people/tables.py
lara_django_people/tasks.py
lara_django_people/urls.py
lara_django_people/views.py
lara_django_people/fixtures/2_entitiy_roles_fix.json
lara_django_people/fixtures/4_entity_class_fix.json
lara_django_people/fixtures/7_extra_data_types_fix.json
lara_django_people/fixtures/9_entities_fix.json
lara_django_people/fixtures/README.md
lara_django_people/grpc/__init__.py
lara_django_people/grpc/handlers.py
lara_django_people/grpc/serializers.py
lara_django_people/grpc/services.py
lara_django_people/management/__init__.py
lara_django_people/management/commands/__init__.py
lara_django_people/rest_api/__init__.py
lara_django_people/rest_api/serializers.py
lara_django_people/rest_api/views.py
lara_django_people/static/lara_django_people/css/project.css
lara_django_people/static/lara_django_people/fonts/.gitkeep
lara_django_people/static/lara_django_people/js/project.js
lara_django_people/static/lara_django_people/js/vendors.js
lara_django_people/static/lara_django_people/sass/custom_bootstrap_vars.scss
lara_django_people/static/lara_django_people/sass/project.scss
lara_django_people/templates/lara_django_people/_detail.html
lara_django_people/templates/lara_django_people/create_form.html
lara_django_people/templates/lara_django_people/delete_form.html
lara_django_people/templates/lara_django_people/delete_selected_form.html
lara_django_people/templates/lara_django_people/entity_detail.html
lara_django_people/templates/lara_django_people/entity_detail_old.html
lara_django_people/templates/lara_django_people/extradata_detail.html
lara_django_people/templates/lara_django_people/larauser_detail.html
lara_django_people/templates/lara_django_people/list.html
lara_django_people-0.2.102.dist-info/METADATA
lara_django_people-0.2.102.dist-info/WHEEL
lara_django_people-0.2.102.dist-info/licenses/AUTHORS.md
lara_django_people-0.2.102.dist-info/licenses/LICENSE
lara_django_people-0.2.102.dist-info/RECORD
