Metadata-Version: 2.4
Name: lara_django_people
Version: 0.2.102
Summary: The lara_people application can be used to organise people and institutions in the LARA database.
Project-URL: Documentation, https://larasuite.gitlab.io/lara-django-people/
Project-URL: Source, https://gitlab.com/larasuite/lara-django-people
Author-email: mark doerr <mark.doerr@uni-greifswald.de>
License: GPLv3+
License-File: AUTHORS.md
License-File: LICENSE
Classifier: Development Status :: 3 - Alpha
Classifier: Intended Audience :: Developers
Classifier: Intended Audience :: Education
Classifier: Intended Audience :: Science/Research
Classifier: Natural Language :: English
Classifier: Operating System :: OS Independent
Classifier: Programming Language :: Python :: 3
Classifier: Programming Language :: Python :: 3.9
Classifier: Programming Language :: Python :: 3.10
Classifier: Programming Language :: Python :: 3.11
Classifier: Programming Language :: Python :: 3.12
Classifier: Topic :: Scientific/Engineering
Classifier: Topic :: Scientific/Engineering :: Bio-Informatics
Classifier: Topic :: Scientific/Engineering :: Chemistry
Classifier: Topic :: Scientific/Engineering :: Information Analysis
Classifier: Topic :: Scientific/Engineering :: Visualization
Requires-Python: >=3.12
Provides-Extra: dev
Requires-Dist: coverage>=7.6; extra == 'dev'
Requires-Dist: pytest-cov>=2.12; extra == 'dev'
Requires-Dist: pytest-xdist>=3.3; extra == 'dev'
Requires-Dist: pytest>=8.3; extra == 'dev'
Requires-Dist: ruff>=0.9; extra == 'dev'
